LICENSE.rst
MANIFEST.in
README.rst
setup.py
django_rethinkdb_sessions.egg-info/PKG-INFO
django_rethinkdb_sessions.egg-info/SOURCES.txt
django_rethinkdb_sessions.egg-info/dependency_links.txt
django_rethinkdb_sessions.egg-info/not-zip-safe
django_rethinkdb_sessions.egg-info/requires.txt
django_rethinkdb_sessions.egg-info/top_level.txt
rethinkdb_sessions/__init__.py
rethinkdb_sessions/main.py