Metadata-Version: 1.1
Name: django-rethinkdb-sessions
Version: 0.0.3
Summary: rethinkdb backed sessions for django
Home-page: http://github.com/maxpresman/django-rethinkdb-sessions
Author: Max Presman
Author-email: max@presman.ca
License: MIT
Platform: UNKNOWN
Classifier: Development Status :: 3 - Alpha
Classifier: Programming Language :: Python :: 2.7
Classifier: Programming Language :: Python :: 2.6
Classifier: Programming Language :: Python :: Implementation :: PyPy
Classifier: Programming Language :: Python :: Implementation :: CPython
Classifier: Framework :: Django
Classifier: Intended Audience :: Developers
Classifier: License :: OSI Approved :: MIT License
